AUTHORS.rst
LICENSE.rst
README.rst
cudamps.py
demo.py
ez_setup.py
setup.py
cudamps.egg-info/PKG-INFO
cudamps.egg-info/SOURCES.txt
cudamps.egg-info/dependency_links.txt
cudamps.egg-info/pbr.json
cudamps.egg-info/requires.txt
cudamps.egg-info/top_level.txt